pyserial-3.2.data/scripts/miniterm.py
pyserial-3.2.dist-info/DESCRIPTION.rst
pyserial-3.2.dist-info/METADATA
pyserial-3.2.dist-info/RECORD
pyserial-3.2.dist-info/WHEEL
pyserial-3.2.dist-info/metadata.json
pyserial-3.2.dist-info/top_level.txt
serial/__init__.py
serial/__init__.pyc
serial/aio.py
serial/rfc2217.py
serial/rfc2217.pyc
serial/rs485.py
serial/rs485.pyc
serial/serialcli.py
serial/serialcli.pyc
serial/serialjava.py
serial/serialjava.pyc
serial/serialposix.py
serial/serialposix.pyc
serial/serialutil.py
serial/serialutil.pyc
serial/serialwin32.py
serial/serialwin32.pyc
serial/win32.py
serial/win32.pyc
serial/threaded/__init__.py
serial/threaded/__init__.pyc
serial/tools/__init__.py
serial/tools/__init__.pyc
serial/tools/hexlify_codec.py
serial/tools/hexlify_codec.pyc
serial/tools/list_ports.py
serial/tools/list_ports.pyc
serial/tools/list_ports_common.py
serial/tools/list_ports_common.pyc
serial/tools/list_ports_linux.py
serial/tools/list_ports_linux.pyc
serial/tools/list_ports_osx.py
serial/tools/list_ports_osx.pyc
serial/tools/list_ports_posix.py
serial/tools/list_ports_posix.pyc
serial/tools/list_ports_windows.py
serial/tools/list_ports_windows.pyc
serial/tools/miniterm.py
serial/tools/miniterm.pyc
serial/urlhandler/__init__.py
serial/urlhandler/__init__.pyc
serial/urlhandler/protocol_alt.py
serial/urlhandler/protocol_alt.pyc
serial/urlhandler/protocol_hwgrep.py
serial/urlhandler/protocol_hwgrep.pyc
serial/urlhandler/protocol_loop.py
serial/urlhandler/protocol_loop.pyc
serial/urlhandler/protocol_rfc2217.py
serial/urlhandler/protocol_rfc2217.pyc
serial/urlhandler/protocol_serve-rfc2217.py
serial/urlhandler/protocol_socket.py
serial/urlhandler/protocol_socket.pyc
serial/urlhandler/protocol_spy.py
serial/urlhandler/protocol_spy.pyc
